pinedantic/__init__.py
pinedantic/client.py
pinedantic-0.0.3.dist-info/METADATA
pinedantic-0.0.3.dist-info/WHEEL
pinedantic-0.0.3.dist-info/RECORD
